{
  "$schema": "https://wails.io/schemas/config.v2.json",
  "name": "cli-tool-center",
  "outputfilename": "cli-tool-center",
  "frontend:install": "npm install",
  "frontend:build": "npm run build",
  "frontend:dev:watcher": "npm run dev",
  "frontend:dev:serverUrl": "http://localhost:5173",
  "author": {
    "name": "gududege",
    "email": "gududege@github"
  },
  "info": {
    "companyName": "Your Company",
    "productName": "CLI Tool Center",
    "productVersion": "0.0.1",
    "copyright": "Copyright © 2026 Your Company",
    "comments": "A tool center for CLI tools"
  }
}
